{
  "0": {
    "minKills": 0,
    "maxKills": 127,
    "checkPlayer": true,
    "checkLight": false,
    "checkRedstone": false,
    "spawnAmount": 0,
    "cooldown": 0
  },
  "1": {
    "minKills": 128,
    "maxKills": 319,
    "checkPlayer": true,
    "checkLight": true,
    "checkRedstone": false,
    "spawnAmount": 2,
    "cooldown": 20
  },
  "2": {
    "minKills": 320,
    "maxKills": 799,
    "checkPlayer": true,
    "checkLight": true,
    "checkRedstone": false,
    "spawnAmount": 4,
    "cooldown": 10
  },
  "3": {
    "minKills": 800,
    "maxKills": 1999,
    "checkPlayer": false,
    "checkLight": true,
    "checkRedstone": false,
    "spawnAmount": 4,
    "cooldown": 5
  },
  "4": {
    "minKills": 2000,
    "maxKills": 4999,
    "checkPlayer": false,
    "checkLight": true,
    "checkRedstone": false,
    "spawnAmount": 4,
    "cooldown": 5
  },
  "5": {
    "minKills": 5000,
    "maxKills": 5000,
    "checkPlayer": false,
    "checkLight": false,
    "checkRedstone": true,
    "spawnAmount": 6,
    "cooldown": 2
  }
}